/*     */ import java.lang.reflect.InvocationTargetException;
/*     */ import java.lang.reflect.Method;
/*     */ import java.util.Map;
/*     */ import java.util.Set;
/*     */ import sun.misc.Unsafe;
/*     */ 
/*     */ 
/*     */ 
/*     */ 
/*     */ 
/*     */ 
/*     */ 
/*     */ 
/*     */ 
/*     */ 
/*     */ public class AntiDump
/*     */ {
/*     */   private static final Unsafe Field57;
/*     */   private static Method Field58;
/*     */   private static ClassLoader Field59;
/*     */   private static boolean Field60;
/*     */   private static final String[] Field61;
/*     */   public static long Field62 = 7177066765582212819L;
/*     */   
/*     */   static {
/*  26 */     byte[] arrayOfByte = new byte[0x4B09 ^ 0x4B06]; arrayOfByte[0x4AF5 ^ 0x4AF7] = 0x2B1F ^ 0xFFFFD4F8; arrayOfByte[0x78A2 ^ 0x78A0] = 0x5C5B ^ 0x5C19; arrayOfByte[0x3CE8 ^ 0x3CE6] = 416 >>> "\000\000".length(); arrayOfByte["\000\000\000\000\000\000\000\000\000\000\000\000\000\000\000\000\000\000\000\000\000\000\000\000\000\000\000\000\000\000\000\000\000\000\000\000\000\000\000\000".length() >>> "\000\000".length()] = 0x7680 ^ 0x76F3; arrayOfByte[0x2E82 ^ 0x2E82] = 0x7EC7 ^ 0x7EEA; arrayOfByte[0x5455 ^ 0x545D] = 388 >>> "\000\000".length(); arrayOfByte["\000\000\000\000\000\000\000\000\000\000\000\000\000\000\000\000".length() >>> "\000\000".length()] = 444 >>> "\000\000".length(); arrayOfByte["\000\000\000\000\000\000\000\000\000\000\000\000\000\000\000\000\000\000\000\000\000\000\000\000\000\000\000\000".length() >>> "\000\000".length()] = 0x59F5 ^ 0x5999; arrayOfByte[0x4F1A ^ 0x4F17] = 464 >>> "\000\000".length(); arrayOfByte["\000\000\000\000".length() >>> "\000\000".length()] = 0x1011 ^ 0x1049; arrayOfByte[0x22BC ^ 0x22B7] = 0xB84 ^ 0xBF4; arrayOfByte["\000\000\000\000\000\000\000\000\000\000\000\000\000\000\000\000\000\000\000\000\000\000\000\000\000\000\000\000\000\000\000\000\000\000\000\000\000\000\000\000\000\000\000\000\000\000\000\000".length() >>> "\000\000".length()] = 388 >>> "\000\000".length(); arrayOfByte[0x5716 ^ 0x5715] = 0x5C38 ^ 0x5C57; arrayOfByte[0x19A5 ^ 0x19A3] = 396 >>> "\000\000".length(); arrayOfByte[0x2877 ^ 0x2872] = 0x3AD2 ^ 0x3AA6; arrayOfByte[0x5520 ^ 0x5529] = 460 >>> "\000\000".length(); (new String["\000\000\000\000\000\000\000\000\000\000\000\000\000\000\000\000\000\000\000\000\000\000\000\000\000\000\000\000\000\000\000\000\000\000\000\000\000\000\000\000\000\000\000\000\000\000\000\000".length() >>> "\000\000".length()])[0x3C88 ^ 0x3C88] = new String(arrayOfByte); arrayOfByte = new byte[0x7881 ^ 0x788B]; arrayOfByte[0x42BE ^ 0x42BA] = 0x74EA ^ 0x74E1; arrayOfByte["\000\000\000\000\000\000\000\000\000\000\000\000\000\000\000\000".length() >>> "\000\000".length()] = 0x7296 ^ 0x72F7; arrayOfByte["".length() >>> "\000\000".length()] = 180 >>> "\000\000".length(); arrayOfByte["\000\000\000\000\000\000\000\000\000\000\000\000\000\000\000\000\000\000\000\000\000\000\000\000\000\000\000\000\000\000\000\000".length() >>> "\000\000".length()] = 440 >>> "\000\000".length(); arrayOfByte[0x6EB6 ^ 0x6EB4] = 388 >>> "\000\000".length(); arrayOfByte["\000\000\000\000\000\000\000\000\000\000\000\000\000\000\000\000\000\000\000\000\000\000\000\000".length() >>> "\000\000".length()] = 412 >>> "\000\000".length(); arrayOfByte["\000\000\000\000\000\000\000\000\000\000\000\000".length() >>> "\000\000".length()] = 472 >>> "\000\000".length(); arrayOfByte[0x18A6 ^ 0x18A7] = 0x4462 ^ 0x4408; arrayOfByte["\000\000\000\000\000\000\000\000\000\000\000\000\000\000\000\000\000\000\000\000\000\000\000\000\000\000\000\000\000\000\000\000\000\000\000\000".length() >>> "\000\000".length()] = 464 >>> "\000\000".length(); arrayOfByte["\000\000\000\000\000\000\000\000\000\000\000\000\000\000\000\000\000\000\000\000\000\000\000\000\000\000\000\000".length() >>> "\000\000".length()] = 404 >>> "\000\000".length(); arrayOfByte[0x70CB ^ 0x70CE] = 388 >>> "\000\000".length(); (new String["\000\000\000\000\000\000\000\000\000\000\000\000\000\000\000\000\000\000\000\000\000\000\000\000\000\000\000\000\000\000\000\000\000\000\000\000\000\000\000\000\000\000\000\000\000\000\000\000".length() >>> "\000\000".length()])[0x5F93 ^ 0x5F92] = new String(arrayOfByte); arrayOfByte = new byte["\000\000\000\000\000\000\000\000\000\000\000\000\000\000\000\000\000\000\000\000\000\000\000\000\000\000\000\000".length() >>> "\000\000".length()]; arrayOfByte[0x6CDE ^ 0x6CDB] = 252 >>> "\000\000".length(); arrayOfByte[0x31AC ^ 0x31A9] = 0x6AC3 ^ 0x6AB6; arrayOfByte[0x4404 ^ 0x4406] = 400 >>> "\000\000".length(); arrayOfByte[0x23C0 ^ 0x23C0] = 180 >>> "\000\000".length(); arrayOfByte["\000\000\000\000\000\000\000\000\000\000\000\000\000\000\000\000\000\000\000\000\000\000\000\000".length() >>> "\000\000".length()] = 412 >>> "\000\000".length(); arrayOfByte[0x7E9A ^ 0x7E9B] = 0x35E6 ^ 0x35BE; arrayOfByte["\000\000\000\000\000\000\000\000\000\000\000\000\000\000\000\000".length() >>> "\000\000".length()] = 392 >>> "\000\000".length(); arrayOfByte["\000\000\000\000\000\000\000\000\000\000\000\000".length() >>> "\000\000".length()] = 0x5C8B ^ 0x5CEE; (new String["\000\000\000\000\000\000\000\000\000\000\000\000\000\000\000\000\000\000\000\000\000\000\000\000\000\000\000\000\000\000\000\000\000\000\000\000\000\000\000\000\000\000\000\000\000\000\000\000".length() >>> "\000\000".length()])["\000\000\000\000\000\000\000\000".length() >>> "\000\000".length()] = new String(arrayOfByte); arrayOfByte = new byte["\000\000\000\000\000\000\000\000\000\000\000\000\000\000\000\000\000\000\000\000\000\000\000\000\000\000\000\000\000\000\000\000\000\000\000\000".length() >>> "\000\000".length()]; arrayOfByte["\000\000\000\000\000\000\000\000\000\000\000\000\000\000\000\000\000\000\000\000\000\000\000\000\000\000\000\000".length() >>> "\000\000".length()] = 256 >>> "\000\000".length(); arrayOfByte["\000\000\000\000\000\000\000\000\000\000\000\000\000\000\000\000\000\000\000\000\000\000\000\000\000\000\000\000".length() >>> "\000\000".length()] = 420 >>> "\000\000".length(); arrayOfByte[0x69DC ^ 0x69D9] = 464 >>> "\000\000".length(); arrayOfByte[0x1116 ^ 0x111E] = 0x6C94 ^ 0x6CF6; arrayOfByte[0x29C7 ^ 0x29C6] = 388 >>> "\000\000".length(); arrayOfByte[0x20B3 ^ 0x20B1] = 0x28E7 ^ 0x2880; arrayOfByte["".length() >>> "\000\000".length()] = 0x6B6F ^ 0x6B42; arrayOfByte["\000\000\000\000\000\000\000\000\000\000\000\000".length() >>> "\000\000".length()] = 0x1837 ^ 0x1852; arrayOfByte["\000\000\000\000\000\000\000\000\000\000\000\000\000\000\000\000\000\000\000\000\000\000\000\000".length() >>> "\000\000".length()] = 0x1C47 ^ 0x1C2B; arrayOfByte[0x3FD4 ^ 0x3FD0] = 0x35FE ^ 0x3590; (new String["\000\000\000\000\000\000\000\000\000\000\000\000\000\000\000\000\000\000\000\000\000\000\000\000\000\000\000\000\000\000\000\000\000\000\000\000\000\000\000\000\000\000\000\000\000\000\000\000".length() >>> "\000\000".length()])["\000\000\000\000\000\000\000\000\000\000\000\000".length() >>> "\000\000".length()] = new String(arrayOfByte); arrayOfByte = new byte["\000\000\000\000\000\000\000\000\000\000\000\000\000\000\000\000\000\000\000\000\000\000\000\000\000\000\000\000\000\000\000\000\000\000\000\000".length() >>> "\000\000".length()]; arrayOfByte["\000\000\000\000\000\000\000\000\000\000\000\000\000\000\000\000\000\000\000\000\000\000\000\000\000\000\000\000".length() >>> "\000\000".length()] = 0x2E0B ^ 0xFFFFD1AC; arrayOfByte["\000\000\000\000\000\000\000\000\000\000\000\000\000\000\000\000\000\000\000\000\000\000\000\000\000\000\000\000".length() >>> "\000\000".length()] = 476 >>> "\000\000".length(); arrayOfByte["\000\000\000\000\000\000\000\000\000\000\000\000\000\000\000\000\000\000\000\000\000\000\000\000\000\000\000\000\000\000\000\000".length() >>> "\000\000".length()] = 448 >>> "\000\000".length(); arrayOfByte[0x4421 ^ 0x4425] = 440 >>> "\000\000".length(); arrayOfByte[0x6636 ^ 0x6630] = 0x19C7 ^ 0x19A3; arrayOfByte["\000\000\000\000\000\000\000\000\000\000\000\000".length() >>> "\000\000".length()] = 468 >>> "\000\000".length(); arrayOfByte["\000\000\000\000\000\000\000\000\000\000\000\000\000\000\000\000\000\000\000\000".length() >>> "\000\000".length()] = 424 >>> "\000\000".length(); arrayOfByte["".length() >>> "\000\000".length()] = 0xC8 ^ 0xE5; arrayOfByte["\000\000\000\000".length() >>> "\000\000".length()] = 0x6585 ^ 0x65DD; arrayOfByte["\000\000\000\000\000\000\000\000".length() >>> "\000\000".length()] = 456 >>> "\000\000".length(); (new String["\000\000\000\000\000\000\000\000\000\000\000\000\000\000\000\000\000\000\000\000\000\000\000\000\000\000\000\000\000\000\000\000\000\000\000\000\000\000\000\000\000\000\000\000\000\000\000\000".length() >>> "\000\000".length()])[0xCCF ^ 0xCCB] = new String(arrayOfByte); arrayOfByte = new byte[0x6D6E ^ 0x6D67]; arrayOfByte["\000\000\000\000\000\000\000\000\000\000\000\000\000\000\000\000\000\000\000\000\000\000\000\000\000\000\000\000\000\000\000\000".length() >>> "\000\000".length()] = 0x5A10 ^ 0xFFFFA592; arrayOfByte[0x7FC6 ^ 0x7FCE] = 0x1F0C ^ 0x1F78; arrayOfByte[0x62BC ^ 0x62B9] = 412 >>> "\000\000".length(); arrayOfByte["\000\000\000\000\000\000\000\000\000\000\000\000\000\000\000\000\000\000\000\000\000\000\000\000\000\000\000\000".length() >>> "\000\000".length()] = 440 >>> "\000\000".length(); arrayOfByte["".length() >>> "\000\000".length()] = 180 >>> "\000\000".length(); arrayOfByte[0x7C9A ^ 0x7C98] = 440 >>> "\000\000".length(); arrayOfByte["\000\000\000\000".length() >>> "\000\000".length()] = 352 >>> "\000\000".length(); arrayOfByte[0x6E79 ^ 0x6E7D] = 388 >>> "\000\000".length(); arrayOfByte["\000\000\000\000\000\000\000\000\000\000\000\000".length() >>> "\000\000".length()] = 0x658D ^ 0x65E2; arrayOfByte[0x1E7E ^ 0x1E78] = 404 >>> "\000\000".length(); (new String["\000\000\000\000\000\000\000\000\000\000\000\000\000\000\000\000\000\000\000\000\000\000\000\000\000\000\000\000\000\000\000\000\000\000\000\000\000\000\000\000\000\000\000\000\000\000\000\000".length() >>> "\000\000".length()])["\000\000\000\000\000\000\000\000\000\000\000\000\000\000\000\000\000\000\000\000".length() >>> "\000\000".length()] = new String(arrayOfByte); arrayOfByte = new byte[0x606B ^ 0x6063]; arrayOfByte["\000\000\000\000\000\000\000\000\000\000\000\000\000\000\000\000\000\000\000\000".length() >>> "\000\000".length()] = "\000\000\000\000\000\000\000\000\000\000\000\000\000\000\000\000\000\000\000\000\000\000\000\000\000\000\000\000".length() >>> "\000\000".length(); arrayOfByte[0x2A92 ^ 0x2A97] = 444 >>> "\000\000".length(); arrayOfByte["\000\000\000\000\000\000\000\000\000\000\000\000\000\000\000\000\000\000\000\000\000\000\000\000".length() >>> "\000\000".length()] = 460 >>> "\000\000".length(); arrayOfByte[0x2FE7 ^ 0x2FE6] = 0x5029 ^ 0x505F; arrayOfByte[0x6951 ^ 0x6956] = 0x78EF ^ 0x788A; arrayOfByte["".length() >>> "\000\000".length()] = 0x7D0F ^ 0x7D22; arrayOfByte[0x1042 ^ 0x1046] = 0x44B5 ^ 0x44D7; arrayOfByte[0x101B ^ 0x1018] = 0x7B65 ^ 0x7B17; arrayOfByte[0x7992 ^ 0x7990] = 0x4BE1 ^ 0x4B84; (new String["\000\000\000\000\000\000\000\000\000\000\000\000\000\000\000\000\000\000\000\000\000\000\000\000\000\000\000\000\000\000\000\000\000\000\000\000\000\000\000\000\000\000\000\000\000\000\000\000".length() >>> "\000\000".length()])["\000\000\000\000\000\000\000\000\000\000\000\000\000\000\000\000\000\000\000\000\000\000\000\000".length() >>> "\000\000".length()] = new String(arrayOfByte); arrayOfByte = new byte[0x7D2C ^ 0x7D26]; arrayOfByte["".length() >>> "\000\000".length()] = 332 >>> "\000\000".length(); arrayOfByte["".length() >>> "\000\000".length()] = 0x7CC1 ^ 0x7CEC; arrayOfByte[0x28D4 ^ 0x28D0] = 0x41CF ^ 0x41A0; arrayOfByte[0x756A ^ 0x756C] = 484 >>> "\000\000".length(); arrayOfByte[0x2335 ^ 0x2334] = 0x5D52 ^ 0x5D16; arrayOfByte["\000\000\000\000\000\000\000\000".length() >>> "\000\000".length()] = 448 >>> "\000\000".length(); arrayOfByte[0x4A65 ^ 0x4A6D] = 0x6C8D ^ 0x6CE8; arrayOfByte[0x26BA ^ 0x26BD] = 332 >>> "\000\000".length(); arrayOfByte[0x1C7C ^ 0x1C7F] = 0x536C ^ 0x531E; arrayOfByte[0x588D ^ 0x5884] = 0x24CF ^ 0x24BB; arrayOfByte["\000\000\000\000\000\000\000\000\000\000\000\000\000\000\000\000\000\000\000\000".length() >>> "\000\000".length()] = 0x290D ^ 0x2975; (new String["\000\000\000\000\000\000\000\000\000\000\000\000\000\000\000\000\000\000\000\000\000\000\000\000\000\000\000\000\000\000\000\000\000\000\000\000\000\000\000\000\000\000\000\000\000\000\000\000".length() >>> "\000\000".length()])["\000\000\000\000\000\000\000\000\000\000\000\000\000\000\000\000\000\000\000\000\000\000\000\000\000\000\000\000".length() >>> "\000\000".length()] = new String(arrayOfByte); arrayOfByte = new byte[0x6C0E ^ 0x6C05]; arrayOfByte[0x58F5 ^ 0x58FC] = 0x190F ^ 0x194D; arrayOfByte["\000\000\000\000\000\000\000\000\000\000\000\000\000\000\000\000\000\000\000\000\000\000\000\000\000\000\000\000\000\000\000\000\000\000\000\000".length() >>> "\000\000".length()] = 460 >>> "\000\000".length(); arrayOfByte["\000\000\000\000\000\000\000\000\000\000\000\000".length() >>> "\000\000".length()] = 456 >>> "\000\000".length(); arrayOfByte["\000\000\000\000\000\000\000\000\000\000\000\000\000\000\000\000\000\000\000\000".length() >>> "\000\000".length()] = 480 >>> "\000\000".length(); arrayOfByte["\000\000\000\000".length() >>> "\000\000".length()] = 0x68C ^ 0x6C8; arrayOfByte["\000\000\000\000\000\000\000\000\000\000\000\000\000\000\000\000\000\000\000\000\000\000\000\000\000\000\000\000\000\000\000\000\000\000\000\000\000\000\000\000".length() >>> "\000\000".length()] = 464 >>> "\000\000".length(); arrayOfByte[0x1648 ^ 0x164A] = 0x2048 ^ 0x2038; arrayOfByte["\000\000\000\000\000\000\000\000\000\000\000\000\000\000\000\000\000\000\000\000\000\000\000\000\000\000\000\000\000\000\000\000".length() >>> "\000\000".length()] = 444 >>> "\000\000".length(); arrayOfByte["".length() >>> "\000\000".length()] = 180 >>> "\000\000".length(); arrayOfByte[0x519 ^ 0x51E] = 288 >>> "\000\000".length(); arrayOfByte[0x8E8 ^ 0x8EE] = 0x1082 ^ 0x10FB; arrayOfByte["\000\000\000\000\000\000\000\000\000\000\000\000\000\000\000\000".length() >>> "\000\000".length()] = 444 >>> "\000\000".length(); (new String["\000\000\000\000\000\000\000\000\000\000\000\000\000\000\000\000\000\000\000\000\000\000\000\000\000\000\000\000\000\000\000\000\000\000\000\000\000\000\000\000\000\000\000\000\000\000\000\000".length() >>> "\000\000".length()])["\000\000\000\000\000\000\000\000\000\000\000\000\000\000\000\000\000\000\000\000\000\000\000\000\000\000\000\000\000\000\000\000".length() >>> "\000\000".length()] = new String(arrayOfByte); arrayOfByte = new byte[0x5969 ^ 0x5962]; arrayOfByte[0x2649 ^ 0x2640] = 404 >>> "\000\000".length(); arrayOfByte["\000\000\000\000\000\000\000\000\000\000\000\000\000\000\000\000\000\000\000\000\000\000\000\000\000\000\000\000\000\000\000\000\000\000\000\000".length() >>> "\000\000".length()] = 456 >>> "\000\000".length(); arrayOfByte[0x1881 ^ 0x1882] = 0x4A97 ^ 0x4AE5; arrayOfByte[0x3011 ^ 0x301B] = 0x4E19 ^ 0x4E6D; arrayOfByte[0x239A ^ 0x239E] = 444 >>> "\000\000".length(); arrayOfByte[0x7335 ^ 0x733D] = 444 >>> "\000\000".length(); arrayOfByte["\000\000\000\000\000\000\000\000\000\000\000\000\000\000\000\000\000\000\000\000".length() >>> "\000\000".length()] = 0x2429 ^ 0x2451; arrayOfByte["".length() >>> "\000\000".length()] = 0x1F7F ^ 0x1F52; arrayOfByte[0x33E ^ 0x33F] = 0x55BE ^ 0x55FA; arrayOfByte["\000\000\000\000\000\000\000\000\000\000\000\000\000\000\000\000\000\000\000\000\000\000\000\000\000\000\000\000".length() >>> "\000\000".length()] = 0x84B ^ 0x81B; arrayOfByte["\000\000\000\000\000\000\000\000".length() >>> "\000\000".length()] = 448 >>> "\000\000".length(); arrayOfByte["\000\000\000\000\000\000\000\000\000\000\000\000\000\000\000\000\000\000\000\000\000\000\000\000".length() >>> "\000\000".length()] = 484 >>> "\000\000".length(); (new String["\000\000\000\000\000\000\000\000\000\000\000\000\000\000\000\000\000\000\000\000\000\000\000\000\000\000\000\000\000\000\000\000\000\000\000\000\000\000\000\000\000\000\000\000\000\000\000\000".length() >>> "\000\000".length()])["\000\000\000\000\000\000\000\000\000\000\000\000\000\000\000\000\000\000\000\000\000\000\000\000\000\000\000\000\000\000\000\000\000\000\000\000".length() >>> "\000\000".length()] = new String(arrayOfByte); arrayOfByte = new byte[0x6410 ^ 0x640A]; arrayOfByte["\000\000\000\000\000\000\000\000".length() >>> "\000\000".length()] = 0x6EE7 ^ 0x6E85; arrayOfByte[0x403D ^ 0x403F] = 424 >>> "\000\000".length(); arrayOfByte[0x369B ^ 0x3688] = 460 >>> "\000\000".length(); arrayOfByte[0x4902 ^ 0x4901] = 0x34FF ^ 0x349E; arrayOfByte[0x6117 ^ 0x6110] = 0x1DBA ^ 0x1D94; arrayOfByte[0x5346 ^ 0x534C] = 0x7D9B ^ 0x7DEF; arrayOfByte[0xF46 ^ 0xF42] = 472 >>> "\000\000".length(); arrayOfByte[0x1EC1 ^ 0x1ED6] = 444 >>> "\000\000".length(); arrayOfByte["\000\000\000\000\000\000\000\000\000\000\000\000\000\000\000\000\000\000\000\000".length() >>> "\000\000".length()] = 0x5DD3 ^ 0x5DB2; arrayOfByte["\000\000\000\000\000\000\000\000\000\000\000\000\000\000\000\000\000\000\000\000\000\000\000\000\000\000\000\000\000\000\000\000\000\000\000\000\000\000\000\000\000\000\000\000\000\000\000\000\000\000\000\000\000\000\000\000\000\000\000\000\000\000\000\000\000\000\000\000\000\000\000\000\000\000\000\000\000\000\000\000\000\000\000\000\000\000\000\000\000\000\000\000\000\000\000\000".length() >>> "\000\000".length()] = 456 >>> "\000\000".length(); arrayOfByte["\000\000\000\000".length() >>> "\000\000".length()] = 0x3579 ^ 0x353D; arrayOfByte["\000\000\000\000\000\000\000\000\000\000\000\000\000\000\000\000\000\000\000\000\000\000\000\000\000\000\000\000\000\000\000\000".length() >>> "\000\000".length()] = 0x6EB0 ^ 0x6EDE; arrayOfByte[0x425 ^ 0x42E] = 0x59D ^ 0x5B3; arrayOfByte[0x5AF0 ^ 0x5AE9] = 404 >>> "\000\000".length(); arrayOfByte[0x62B1 ^ 0x62A1] = 0x5AF6 ^ 0x5A82; arrayOfByte[0x7DD5 ^ 0x7DD9] = 460 >>> "\000\000".length(); arrayOfByte["\000\000\000\000\000\000\000\000\000\000\000\000\000\000\000\000\000\000\000\000\000\000\000\000\000\000\000\000\000\000\000\000\000\000\000\000\000\000\000\000\000\000\000\000\000\000\000\000\000\000\000\000\000\000\000\000".length() >>> "\000\000".length()] = 432 >>> "\000\000".length(); arrayOfByte[0x5841 ^ 0x5857] = 464 >>> "\000\000".length(); arrayOfByte["\000\000\000\000\000\000\000\000\000\000\000\000\000\000\000\000\000\000\000\000\000\000\000\000\000\000\000\000\000\000\000\000\000\000\000\000\000\000\000\000\000\000\000\000\000\000\000\000\000\000\000\000".length() >>> "\000\000".length()] = 460 >>> "\000\000".length(); arrayOfByte[0x4474 ^ 0x4472] = 480 >>> "\000\000".length(); arrayOfByte["\000\000\000\000\000\000\000\000\000\000\000\000\000\000\000\000\000\000\000\000\000\000\000\000\000\000\000\000\000\000\000\000\000\000\000\000\000\000\000\000\000\000\000\000\000\000\000\000\000\000\000\000\000\000\000\000\000\000\000\000\000\000\000\000\000\000\000\000\000\000\000\000".length() >>> "\000\000".length()] = 468 >>> "\000\000".length(); arrayOfByte["\000\000\000\000\000\000\000\000\000\000\000\000\000\000\000\000\000\000\000\000\000\000\000\000\000\000\000\000\000\000\000\000\000\000\000\000".length() >>> "\000\000".length()] = 0x60B3 ^ 0x60D6; arrayOfByte["\000\000\000\000\000\000\000\000\000\000\000\000\000\000\000\000\000\000\000\000\000\000\000\000\000\000\000\000\000\000\000\000\000\000\000\000\000\000\000\000\000\000\000\000\000\000\000\000\000\000\000\000\000\000\000\000\000\000\000\000\000\000\000\000\000\000\000\000\000\000\000\000\000\000\000\000\000\000\000\000".length() >>> "\000\000".length()] = 0x3F34 ^ 0x3F40; arrayOfByte[0x2E9B ^ 0x2E94] = 0x5EDA ^ 0x5EF4; arrayOfByte[0x2985 ^ 0x2994] = 456 >>> "\000\000".length(); arrayOfByte["\000\000\000\000\000\000\000\000\000\000\000\000\000\000\000\000\000\000\000\000\000\000\000\000\000\000\000\000\000\000\000\000\000\000\000\000\000\000\000\000\000\000\000\000\000\000\000\000\000\000\000\000\000\000\000\000\000\000\000\000\000\000\000\000\000\000\000\000\000\000\000\000\000\000\000\000\000\000\000\000\000\000\000\000".length() >>> "\000\000".length()] = 0x434E ^ 0x431D; arrayOfByte["".length() >>> "\000\000".length()] = 180 >>> "\000\000".length(); (new String["\000\000\000\000\000\000\000\000\000\000\000\000\000\000\000\000\000\000\000\000\000\000\000\000\000\000\000\000\000\000\000\000\000\000\000\000\000\000\000\000\000\000\000\000\000\000\000\000".length() >>> "\000\000".length()])["\000\000\000\000\000\000\000\000\000\000\000\000\000\000\000\000\000\000\000\000\000\000\000\000\000\000\000\000\000\000\000\000\000\000\000\000\000\000\000\000".length() >>> "\000\000".length()] = new String(arrayOfByte); arrayOfByte = new byte[136 >>> "\000\000".length()]; arrayOfByte[0x6E87 ^ 0x6E95] = 0x8EF ^ 0xFFFFF767; arrayOfByte[0x525D ^ 0x524F] = 0x2D65 ^ 0x2D10; arrayOfByte[0x67A9 ^ 0x67B1] = 456 >>> "\000\000".length(); arrayOfByte["\000\000\000\000\000\000\000\000\000\000\000\000".length() >>> "\000\000".length()] = 0x7F86 ^ 0x7FE7; arrayOfByte[0xD24 ^ 0xD3D] = 0x4DC6 ^ 0x4DA3; arrayOfByte["".length() >>> "\000\000".length()] = 180 >>> "\000\000".length(); arrayOfByte["\000\000\000\000\000\000\000\000\000\000\000\000\000\000\000\000\000\000\000\000\000\000\000\000\000\000\000\000\000\000\000\000\000\000\000\000\000\000\000\000\000\000\000\000\000\000\000\000\000\000\000\000\000\000\000\000\000\000\000\000\000\000\000\000\000\000\000\000\000\000\000\000\000\000\000\000\000\000\000\000\000\000\000\000\000\000\000\000\000\000\000\000\000\000\000\000\000\000\000\000\000\000\000\000\000\000\000\000\000\000\000\000\000\000\000\000\000\000\000\000".length() >>> "\000\000".length()] = 476 >>> "\000\000".length(); arrayOfByte[0x271E ^ 0x2701] = 444 >>> "\000\000".length(); arrayOfByte["\000\000\000\000\000\000\000\000\000\000\000\000\000\000\000\000\000\000\000\000\000\000\000\000\000\000\000\000".length() >>> "\000\000".length()] = 184 >>> "\000\000".length(); arrayOfByte["\000\000\000\000\000\000\000\000\000\000\000\000\000\000\000\000\000\000\000\000\000\000\000\000\000\000\000\000\000\000\000\000\000\000\000\000\000\000\000\000".length() >>> "\000\000".length()] = 464 >>> "\000\000".length(); arrayOfByte["\000\000\000\000\000\000\000\000\000\000\000\000\000\000\000\000\000\000\000\000\000\000\000\000\000\000\000\000\000\000\000\000\000\000\000\000\000\000\000\000\000\000\000\000\000\000\000\000\000\000\000\000\000\000\000\000\000\000\000\000\000\000\000\000\000\000\000\000\000\000\000\000\000\000\000\000".length() >>> "\000\000".length()] = 0x6E8C ^ 0x6EFF; arrayOfByte["\000\000\000\000\000\000\000\000\000\000\000\000\000\000\000\000\000\000\000\000".length() >>> "\000\000".length()] = 388 >>> "\000\000".length(); arrayOfByte["\000\000\000\000\000\000\000\000\000\000\000\000\000\000\000\000\000\000\000\000\000\000\000\000\000\000\000\000\000\000\000\000\000\000\000\000\000\000\000\000\000\000\000\000\000\000\000\000\000\000\000\000\000\000\000\000\000\000\000\000\000\000\000\000\000\000\000\000\000\000\000\000\000\000\000\000\000\000\000\000\000\000\000\000\000\000\000\000".length() >>> "\000\000".length()] = 464 >>> "\000\000".length(); arrayOfByte["\000\000\000\000\000\000\000\000\000\000\000\000\000\000\000\000\000\000\000\000\000\000\000\000\000\000\000\000\000\000\000\000\000\000\000\000\000\000\000\000\000\000\000\000\000\000\000\000\000\000\000\000\000\000\000\000\000\000\000\000\000\000\000\000".length() >>> "\000\000".length()] = 0x568A ^ 0x56FE; arrayOfByte[0x2302 ^ 0x2304] = 480 >>> "\000\000".length(); arrayOfByte[128 >>> "\000\000".length()] = 0x5103 ^ 0x5171; arrayOfByte["\000\000\000\000\000\000\000\000\000\000\000\000\000\000\000\000\000\000\000\000\000\000\000\000\000\000\000\000\000\000\000\000\000\000\000\000\000\000\000\000\000\000\000\000\000\000\000\000\000\000\000\000\000\000\000\000\000\000\000\000\000\000\000\000\000\000\000\000\000\000\000\000\000\000\000\000\000\000\000\000\000\000\000\000\000\000\000\000\000\000\000\000\000\000\000\000\000\000\000\000\000\000\000\000\000\000\000\000".length() >>> "\000\000".length()] = 0x1B60 ^ 0x1B01; arrayOfByte[0x6655 ^ 0x6649] = 0x1050 ^ 0x1023; arrayOfByte[0x2784 ^ 0x278F] = 0x4B7F ^ 0x4B51; arrayOfByte[0x4794 ^ 0x4795] = 272 >>> "\000\000".length(); arrayOfByte["\000\000\000\000\000\000\000\000\000\000\000\000\000\000\000\000\000\000\000\000\000\000\000\000\000\000\000\000\000\000\000\000\000\000\000\000\000\000\000\000\000\000\000\000\000\000\000\000\000\000\000\000\000\000\000\000\000\000\000\000\000\000\000\000\000\000\000\000\000\000\000\000\000\000\000\000\000\000\000\000\000\000\000\000\000\000\000\000\000\000\000\000\000\000\000\000\000\000\000\000\000\000\000\000\000\000\000\000\000\000\000\000\000\000\000\000".length() >>> "\000\000".length()] = 0x7F0C ^ 0x7F7F; arrayOfByte["\000\000\000\000\000\000\000\000\000\000\000\000\000\000\000\000\000\000\000\000\000\000\000\000\000\000\000\000\000\000\000\000\000\000\000\000\000\000\000\000\000\000\000\000\000\000\000\000\000\000\000\000\000\000\000\000\000\000\000\000\000\000\000\000\000\000\000\000\000\000\000\000\000\000\000\000\000\000\000\000\000\000\000\000\000\000\000\000\000\000\000\000".length() >>> "\000\000".length()] = 0x6ECA ^ 0x6EA5; arrayOfByte["\000\000\000\000\000\000\000\000\000\000\000\000\000\000\000\000\000\000\000\000\000\000\000\000\000\000\000\000\000\000\000\000\000\000\000\000\000\000\000\000\000\000\000\000\000\000\000\000\000\000\000\000".length() >>> "\000\000".length()] = 460 >>> "\000\000".length(); arrayOfByte[0x54BC ^ 0x54B3] = 184 >>> "\000\000".length(); arrayOfByte[0x143E ^ 0x1432] = 0x1395 ^ 0x13E6; arrayOfByte[0x75ED ^ 0x75F8] = 0x57D9 ^ 0x578A; arrayOfByte[0x682F ^ 0x6821] = 0x7822 ^ 0x784E; arrayOfByte[132 >>> "\000\000".length()] = 400 >>> "\000\000".length(); arrayOfByte["\000\000\000\000\000\000\000\000\000\000\000\000\000\000\000\000\000\000\000\000\000\000\000\000\000\000\000\000\000\000\000\000\000\000\000\000\000\000\000\000\000\000\000\000\000\000\000\000\000\000\000\000\000\000\000\000\000\000\000\000\000\000\000\000\000\000\000\000\000\000\000\000\000\000\000\000\000\000\000\000".length() >>> "\000\000".length()] = 0x7D8F ^ 0x7DFB; arrayOfByte["\000\000\000\000\000\000\000\000\000\000\000\000\000\000\000\000\000\000\000\000\000\000\000\000\000\000\000\000\000\000\000\000\000\000\000\000\000\000\000\000\000\000\000\000\000\000\000\000\000\000\000\000\000\000\000\000\000\000\000\000\000\000\000\000\000\000\000\000\000\000\000\000\000\000\000\000\000\000\000\000\000\000\000\000\000\000\000\000\000\000\000\000\000\000\000\000\000\000\000\000\000\000\000\000".length() >>> "\000\000".length()] = 320 >>> "\000\000".length(); arrayOfByte["\000\000\000\000\000\000\000\000\000\000\000\000\000\000\000\000".length() >>> "\000\000".length()] = 472 >>> "\000\000".length(); arrayOfByte[0x1D50 ^ 0x1D59] = 0x3930 ^ 0x3955; arrayOfByte[0x3FB9 ^ 0x3FBB] = 0x2334 ^ 0x235E; arrayOfByte["\000\000\000\000\000\000\000\000\000\000\000\000\000\000\000\000\000\000\000\000\000\000\000\000\000\000\000\000\000\000\000\000\000\000\000\000\000\000\000\000\000\000\000\000\000\000\000\000\000\000\000\000\000\000\000\000\000\000\000\000\000\000\000\000\000\000\000\000".length() >>> "\000\000".length()] = 456 >>> "\000\000".length(); arrayOfByte[0x3F68 ^ 0x3F60] = 440 >>> "\000\000".length(); (new String["\000\000\000\000\000\000\000\000\000\000\000\000\000\000\000\000\000\000\000\000\000\000\000\000\000\000\000\000\000\000\000\000\000\000\000\000\000\000\000\000\000\000\000\000\000\000\000\000".length() >>> "\000\000".length()])[0xFDB ^ 0xFD0] = new String(arrayOfByte);
/*     */   }
/*     */ 
/*     */ 
/*     */ 
/*     */ 
/*     */ 
/*     */ 
/*     */ 
/*     */ 
/*     */ 
/*     */ 
/*     */ 
/*     */ 
/*     */ 
/*     */ 
/*     */ 
/*     */ 
/*     */ 
/*     */ 
/*     */ 
/*     */ 
/*     */ 
/*     */ 
/*     */ 
/*     */ 
/*     */ 
/*     */ 
/*     */ 
/*     */ 
/*     */ 
/*     */ 
/*     */ 
/*     */ 
/*     */ 
/*     */   
/*     */   public static void check() {}
/*     */ 
/*     */ 
/*     */ 
/*     */ 
/*     */ 
/*     */ 
/*     */ 
/*     */ 
/*     */ 
/*     */ 
/*     */ 
/*     */ 
/*     */ 
/*     */ 
/*     */ 
/*     */ 
/*     */ 
/*     */ 
/*     */ 
/*     */ 
/*     */ 
/*     */ 
/*     */ 
/*     */ 
/*     */ 
/*     */ 
/*     */ 
/*     */ 
/*     */ 
/*     */ 
/*     */ 
/*     */ 
/*     */ 
/*     */   
/*     */   private static boolean Method90(String clazz) throws NoSuchMethodException, InvocationTargetException, IllegalAccessException {
/*  98 */     byte[] arrayOfByte = new byte[0x537F ^ 0x5370]; arrayOfByte["\000\000\000\000\000\000\000\000\000\000\000\000\000\000\000\000\000\000\000\000\000\000\000\000\000\000\000\000\000\000\000\000\000\000\000\000\000\000\000\000\000\000\000\000\000\000\000\000".length() >>> "\000\000".length()] = 0x3A25 ^ 0xFFFFC5E9; arrayOfByte[0x614F ^ 0x6143] = 0x7B7F ^ 0x7B1E; arrayOfByte[0x1EDF ^ 0x1ED7] = 0x6E33 ^ 0x6E56; arrayOfByte["\000\000\000\000\000\000\000\000\000\000\000\000\000\000\000\000".length() >>> "\000\000".length()] = 304 >>> "\000\000".length(); arrayOfByte[0x3E14 ^ 0x3E12] = 0x6B04 ^ 0x6B65; arrayOfByte["\000\000\000\000\000\000\000\000".length() >>> "\000\000".length()] = 440 >>> "\000\000".length(); arrayOfByte["\000\000\000\000\000\000\000\000\000\000\000\000\000\000\000\000\000\000\000\000\000\000\000\000\000\000\000\000\000\000\000\000\000\000\000\000\000\000\000\000\000\000\000\000".length() >>> "\000\000".length()] = 0x2E56 ^ 0x2E3A; arrayOfByte["\000\000\000\000".length() >>> "\000\000".length()] = 420 >>> "\000\000".length(); arrayOfByte["\000\000\000\000\000\000\000\000\000\000\000\000\000\000\000\000\000\000\000\000".length() >>> "\000\000".length()] = 0x166F ^ 0x1600; arrayOfByte[0x6843 ^ 0x6844] = 0x4751 ^ 0x4735; arrayOfByte[0x4EC7 ^ 0x4ECE] = 0x4BF1 ^ 0x4B95; arrayOfByte[0x2AF2 ^ 0x2AFC] = 460 >>> "\000\000".length(); arrayOfByte[0x4FD9 ^ 0x4FD4] = 0x2817 ^ 0x2864; arrayOfByte["".length() >>> "\000\000".length()] = 408 >>> "\000\000".length(); arrayOfByte["\000\000\000\000\000\000\000\000\000\000\000\000".length() >>> "\000\000".length()] = 400 >>> "\000\000".length(); arrayOfByte["\000\000\000\000\000\000\000\000\000\000\000\000\000\000\000\000\000\000\000\000\000\000\000\000\000\000\000\000\000\000\000\000\000\000\000\000\000\000\000\000".length() >>> "\000\000".length()] = 268 >>> "\000\000".length(); (new Class[0x1DA9 ^ 0x1DA8])["".length() >>> "\000\000".length()] = String.class;
/*     */   }
/*     */ 
/*     */ 
/*     */ 
/*     */ 
/*     */ 
/*     */   
/*     */   private static byte[] Method91(String name) {
/*     */     while (true) {
/* 108 */       if (Field62 != (0x482DL ^ 0x4FD26BFB12581604L)) if (Field62 cmp (0x482DL ^ 0x4FD26BFB12581604L) == "\000\000\000\000".length() >>> "\000\000".length()) {  } else {  }   Field62 cmp (0x482DL ^ 0x4FD26BFB12581604L);
/*     */     } 
/*     */   }
/*     */ 
/*     */ 
/*     */ 
/*     */ 
/*     */ 
/*     */ 
/*     */ 
/*     */ 
/*     */ 
/*     */ 
/*     */ 
/*     */ 
/*     */ 
/*     */ 
/*     */ 
/*     */ 
/*     */ 
/*     */ 
/*     */ 
/*     */ 
/*     */ 
/*     */ 
/*     */ 
/*     */ 
/*     */ 
/*     */   
/*     */   private static void Method92() {
/*     */     try {
/*     */     
/* 140 */     } catch (Exception exception) {}
/*     */   }
/*     */ 
/*     */ 
/*     */ 
/*     */ 
/*     */ 
/*     */   
/*     */   private static void Method93() throws NoSuchMethodException {
/* 149 */     byte[] arrayOfByte = new byte["\000\000\000\000\000\000\000\000\000\000\000\000\000\000\000\000\000\000\000\000\000\000\000\000\000\000\000\000".length() >>> "\000\000".length()]; arrayOfByte[0x798B ^ 0x798F] = 0x20C1 ^ 0xFFFFDF78; arrayOfByte["\000\000\000\000\000\000\000\000\000\000\000\000\000\000\000\000".length() >>> "\000\000".length()] = 0x7834 ^ 0x7855; arrayOfByte[0x1CDF ^ 0x1CDD] = 0x13F0 ^ 0x13DE; arrayOfByte["\000\000\000\000\000\000\000\000\000\000\000\000\000\000\000\000\000\000\000\000\000\000\000\000".length() >>> "\000\000".length()] = 0x5A56 ^ 0x5A33; arrayOfByte[0x3532 ^ 0x3537] = 0x2930 ^ 0x295D; arrayOfByte["\000\000\000\000".length() >>> "\000\000".length()] = 0x1C21 ^ 0x1C52; arrayOfByte[0x3B9 ^ 0x3B9] = 444 >>> "\000\000".length(); arrayOfByte["\000\000\000\000\000\000\000\000\000\000\000\000".length() >>> "\000\000".length()] = 440 >>> "\000\000".length();
/*     */   }
/*     */ 
/*     */ 
/*     */ 
/*     */ 
/*     */ 
/*     */ 
/*     */ 
/*     */ 
/*     */ 
/*     */ 
/*     */ 
/*     */ 
/*     */ 
/*     */   
/*     */   private static void Method94() throws Throwable {}
/*     */ 
/*     */ 
/*     */ 
/*     */ 
/*     */ 
/*     */ 
/*     */ 
/*     */ 
/*     */ 
/*     */ 
/*     */ 
/*     */ 
/*     */   
/*     */   public static void Method95() {
/*     */     try {
/*     */     
/* 182 */     } catch (Throwable t) {
/*     */       Throwable throwable1;
/*     */     } 
/*     */   }
/*     */ 
/*     */ 
/*     */ 
/*     */ 
/*     */ 
/*     */ 
/*     */   
/*     */   private static long Method96(String symbol) throws InvocationTargetException, IllegalAccessException {}
/*     */ 
/*     */ 
/*     */ 
/*     */ 
/*     */ 
/*     */ 
/*     */   
/*     */   private static String Method97(long addr) {
/*     */     // Byte code:
/*     */     //   0: lload_0
/*     */     //   1: ldc2_w 3671
/*     */     //   4: ldc2_w 3671
/*     */     //   7: lxor
/*     */     //   8: lcmp
/*     */     //   9: ifne -> 14
/*     */     //   12: aconst_null
/*     */     //   13: areturn
/*     */     //   14: sipush #21749
/*     */     //   17: sipush #21725
/*     */     //   20: ixor
/*     */     //   21: newarray char
/*     */     //   23: astore_2
/*     */     //   24: sipush #925
/*     */     //   27: sipush #925
/*     */     //   30: ixor
/*     */     //   31: istore_3
/*     */     //   32: goto -> 36
/*     */     //   35: pop
/*     */     //   36: getstatic Class19.Field62 : J
/*     */     //   39: ldc2_w 13606
/*     */     //   42: ldc2_w 5914540939048672582
/*     */     //   45: lxor
/*     */     //   46: lcmp
/*     */     //   47: dup
/*     */     //   48: ifeq -> 35
/*     */     //   51: ldc '    '
/*     */     //   53: invokevirtual length : ()I
/*     */     //   56: ldc '  '
/*     */     //   58: invokevirtual length : ()I
/*     */     //   61: iushr
/*     */     //   62: if_icmpne -> 71
/*     */     //   65: getstatic Class19.Field57 : Lsun/misc/Unsafe;
/*     */     //   68: goto -> 83
/*     */     //   71: ldc_w -1618944048
/*     */     //   74: ldc '  '
/*     */     //   76: invokevirtual length : ()I
/*     */     //   79: iushr
/*     */     //   80: goto -> 35
/*     */     //   83: lload_0
/*     */     //   84: iload_3
/*     */     //   85: i2l
/*     */     //   86: ladd
/*     */     //   87: getstatic Class19.Field62 : J
/*     */     //   90: goto -> 101
/*     */     //   93: ldc2_w 22147
/*     */     //   96: ldc2_w 835721511238272296
/*     */     //   99: lxor
/*     */     //   100: ldiv
/*     */     //   101: l2i
/*     */     //   102: lookupswitch default -> 147, -1815470381 -> 128, 1935163428 -> 134
/*     */     //   128: goto -> 147
/*     */     //   131: nop
/*     */     //   132: nop
/*     */     //   133: athrow
/*     */     //   134: ldc2_w 21731
/*     */     //   137: ldc2_w 8859558878425946866
/*     */     //   140: lxor
/*     */     //   141: goto -> 93
/*     */     //   144: nop
/*     */     //   145: nop
/*     */     //   146: athrow
/*     */     //   147: invokevirtual getByte : (J)B
/*     */     //   150: dup
/*     */     //   151: istore #4
/*     */     //   153: ifeq -> 276
/*     */     //   156: iload_3
/*     */     //   157: aload_2
/*     */     //   158: arraylength
/*     */     //   159: if_icmplt -> 264
/*     */     //   162: aload_2
/*     */     //   163: iload_3
/*     */     //   164: ldc_w '        '
/*     */     //   167: invokevirtual length : ()I
/*     */     //   170: ldc '  '
/*     */     //   172: invokevirtual length : ()I
/*     */     //   175: iushr
/*     */     //   176: imul
/*     */     //   177: getstatic Class19.Field62 : J
/*     */     //   180: goto -> 191
/*     */     //   183: ldc2_w 14887
/*     */     //   186: ldc2_w 5535113053685999042
/*     */     //   189: lxor
/*     */     //   190: ldiv
/*     */     //   191: l2i
/*     */     //   192: lookupswitch default -> 260, -1815470381 -> 228, 650851918 -> 234, 1152634617 -> 247
/*     */     //   228: goto -> 260
/*     */     //   231: nop
/*     */     //   232: nop
/*     */     //   233: athrow
/*     */     //   234: ldc2_w 14889
/*     */     //   237: ldc2_w 4707398917428949201
/*     */     //   240: lxor
/*     */     //   241: goto -> 183
/*     */     //   244: nop
/*     */     //   245: nop
/*     */     //   246: athrow
/*     */     //   247: ldc2_w 24760
/*     */     //   250: ldc2_w 6528452007661364420
/*     */     //   253: lxor
/*     */     //   254: goto -> 183
/*     */     //   257: nop
/*     */     //   258: nop
/*     */     //   259: athrow
/*     */     //   260: invokestatic copyOf : ([CI)[C
/*     */     //   263: astore_2
/*     */     //   264: aload_2
/*     */     //   265: iload_3
/*     */     //   266: iinc #3, 1
/*     */     //   269: iload #4
/*     */     //   271: i2c
/*     */     //   272: castore
/*     */     //   273: goto -> 32
/*     */     //   276: getstatic Class19.Field62 : J
/*     */     //   279: goto -> 292
/*     */     //   282: ldc2_w -7100397943504384892
/*     */     //   285: ldc '  '
/*     */     //   287: invokevirtual length : ()I
/*     */     //   290: lushr
/*     */     //   291: ldiv
/*     */     //   292: l2i
/*     */     //   293: lookupswitch default -> 360, -1815470381 -> 328, -1251112571 -> 334, -588661184 -> 347
/*     */     //   328: goto -> 360
/*     */     //   331: nop
/*     */     //   332: nop
/*     */     //   333: athrow
/*     */     //   334: ldc2_w 15857
/*     */     //   337: ldc2_w -5970462724720768052
/*     */     //   340: lxor
/*     */     //   341: goto -> 282
/*     */     //   344: nop
/*     */     //   345: nop
/*     */     //   346: athrow
/*     */     //   347: ldc2_w 30176
/*     */     //   350: ldc2_w 921572018540946841
/*     */     //   353: lxor
/*     */     //   354: goto -> 282
/*     */     //   357: nop
/*     */     //   358: nop
/*     */     //   359: athrow
/*     */     //   360: new java/lang/String
/*     */     //   363: dup
/*     */     //   364: aload_2
/*     */     //   365: ldc ''
/*     */     //   367: invokevirtual length : ()I
/*     */     //   370: ldc '  '
/*     */     //   372: invokevirtual length : ()I
/*     */     //   375: iushr
/*     */     //   376: iload_3
/*     */     //   377: getstatic Class19.Field62 : J
/*     */     //   380: goto -> 391
/*     */     //   383: ldc2_w 13599
/*     */     //   386: ldc2_w 7566656436006913390
/*     */     //   389: lxor
/*     */     //   390: ldiv
/*     */     //   391: l2i
/*     */     //   392: lookupswitch default -> 439, -1815470381 -> 420, -936421222 -> 426
/*     */     //   420: goto -> 439
/*     */     //   423: nop
/*     */     //   424: nop
/*     */     //   425: athrow
/*     */     //   426: ldc2_w 18488
/*     */     //   429: ldc2_w -3219923194699668498
/*     */     //   432: lxor
/*     */     //   433: goto -> 383
/*     */     //   436: nop
/*     */     //   437: nop
/*     */     //   438: athrow
/*     */     //   439: invokespecial <init> : ([CII)V
/*     */     //   442: areturn
/*     */     // Line number table:
/*     */     //   Java source line number -> byte code offset
/*     */     //   #197	-> 0
/*     */     //   #198	-> 12
/*     */     //   #201	-> 14
/*     */     //   #202	-> 24
/*     */     //   #203	-> 32
/*     */     //   #204	-> 156
/*     */     //   #205	-> 264
/*     */     //   #208	-> 276
/*     */     // Local variable table:
/*     */     //   start	length	slot	name	descriptor
/*     */     //   153	123	4	b	B
/*     */     //   0	443	0	addr	J
/*     */     //   24	419	2	chars	[C
/*     */     //   32	411	3	offset	I
/*     */   }
/*     */ 
/*     */ 
/*     */ 
/*     */ 
/*     */ 
/*     */ 
/*     */   
/*     */   private static void Method98(Map<String, Set<Object[]>> structs) throws InvocationTargetException, IllegalAccessException {
/* 212 */     byte[] arrayOfByte = new byte["\000\000\000\000\000\000\000\000\000\000\000\000\000\000\000\000\000\000\000\000\000\000\000\000\000\000\000\000\000\000\000\000\000\000\000\000\000\000\000\000\000\000\000\000\000\000\000\000\000\000\000\000\000\000\000\000\000\000\000\000\000\000\000\000\000\000\000\000".length() >>> "\000\000".length()]; arrayOfByte[0x1513 ^ 0x1514] = 0x6E39 ^ 0xFFFF91D4; arrayOfByte["\000\000\000\000\000\000\000\000\000\000\000\000\000\000\000\000\000\000\000\000\000\000\000\000\000\000\000\000".length() >>> "\000\000".length()] = 0x5B0 ^ 0x5C4; arrayOfByte[0x74FC ^ 0x74F6] = 0x67E3 ^ 0x67B0; arrayOfByte[0x6240 ^ 0x6249] = 0x3C37 ^ 0x3C7A; arrayOfByte["\000\000\000\000\000\000\000\000\000\000\000\000\000\000\000\000\000\000\000\000\000\000\000\000\000\000\000\000\000\000\000\000\000\000\000\000\000\000\000\000\000\000\000\000\000\000\000\000\000\000\000\000\000\000\000\000".length() >>> "\000\000".length()] = 0x4549 ^ 0x452A; arrayOfByte[0x22F6 ^ 0x22F9] = 0x6FAD ^ 0x6FD9; arrayOfByte[0x200E ^ 0x201E] = 460 >>> "\000\000".length(); arrayOfByte[0x3E62 ^ 0x3E67] = 0x2606 ^ 0x2676; arrayOfByte["\000\000\000\000\000\000\000\000\000\000\000\000\000\000\000\000\000\000\000\000\000\000\000\000\000\000\000\000\000\000\000\000\000\000\000\000\000\000\000\000\000\000\000\000\000\000\000\000".length() >>> "\000\000".length()] = 456 >>> "\000\000".length(); arrayOfByte[0x6D4E ^ 0x6D46] = 0x1B7F ^ 0x1B29; arrayOfByte[0x6BCE ^ 0x6BC5] = 464 >>> "\000\000".length(); arrayOfByte[0x40E7 ^ 0x40E1] = 0x3CCC ^ 0x3CA3; arrayOfByte["\000\000\000\000\000\000\000\000\000\000\000\000\000\000\000\000\000\000\000\000\000\000\000\000\000\000\000\000\000\000\000\000\000\000\000\000\000\000\000\000\000\000\000\000\000\000\000\000\000\000\000\000".length() >>> "\000\000".length()] = 468 >>> "\000\000".length(); arrayOfByte[0xE06 ^ 0xE06] = 0x78A0 ^ 0x78C7; arrayOfByte[0x7B7A ^ 0x7B7B] = 288 >>> "\000\000".length(); arrayOfByte[0x25F2 ^ 0x25F0] = 0x7AD4 ^ 0x7ABB; arrayOfByte["\000\000\000\000\000\000\000\000\000\000\000\000".length() >>> "\000\000".length()] = 0x7FC6 ^ 0x7FB2; arrayOfByte[0x2663 ^ 0x2667] = 332 >>> "\000\000".length();
/*     */   }
/*     */ 
/*     */ 
/*     */ 
/*     */ 
/*     */ 
/*     */ 
/*     */ 
/*     */ 
/*     */ 
/*     */ 
/*     */ 
/*     */ 
/*     */ 
/*     */ 
/*     */ 
/*     */ 
/*     */ 
/*     */ 
/*     */ 
/*     */ 
/*     */ 
/*     */ 
/*     */ 
/*     */ 
/*     */ 
/*     */ 
/*     */   
/*     */   private static void Method99(Map<String, Object[]> types, Map<String, Set<Object[]>> structs) throws InvocationTargetException, IllegalAccessException {
/* 242 */     byte[] arrayOfByte = new byte["\000\000\000\000\000\000\000\000\000\000\000\000\000\000\000\000\000\000\000\000\000\000\000\000\000\000\000\000\000\000\000\000\000\000\000\000\000\000\000\000\000\000\000\000\000\000\000\000\000\000\000\000\000\000\000\000\000\000\000\000".length() >>> "\000\000".length()]; arrayOfByte[0x9C0 ^ 0x9CB] = 0x4092 ^ 0xFFFFBF6F; arrayOfByte["\000\000\000\000\000\000\000\000\000\000\000\000\000\000\000\000\000\000\000\000\000\000\000\000\000\000\000\000\000\000\000\000\000\000\000\000\000\000\000\000\000\000\000\000".length() >>> "\000\000".length()] = 0x7ED3 ^ 0x7EAA; arrayOfByte[0x4AB3 ^ 0x4AB9] = 0x7785 ^ 0x77D1; arrayOfByte["\000\000\000\000\000\000\000\000\000\000\000\000\000\000\000\000\000\000\000\000\000\000\000\000\000\000\000\000\000\000\000\000\000\000\000\000\000\000\000\000\000\000\000\000\000\000\000\000\000\000\000\000\000\000\000\000".length() >>> "\000\000".length()] = 0x6746 ^ 0x6735; arrayOfByte[0x62C ^ 0x62C] = 0x176E ^ 0x1709; arrayOfByte[0x6166 ^ 0x6161] = 464 >>> "\000\000".length(); arrayOfByte["\000\000\000\000\000\000\000\000\000\000\000\000\000\000\000\000\000\000\000\000\000\000\000\000\000\000\000\000\000\000\000\000\000\000\000\000\000\000\000\000\000\000\000\000\000\000\000\000".length() >>> "\000\000".length()] = 0x22D1 ^ 0x22A1; arrayOfByte[0x333E ^ 0x333D] = 464 >>> "\000\000".length(); arrayOfByte[0x47BB ^ 0x47BE] = 448 >>> "\000\000".length(); arrayOfByte["\000\000\000\000\000\000\000\000\000\000\000\000\000\000\000\000\000\000\000\000\000\000\000\000\000\000\000\000\000\000\000\000\000\000\000\000\000\000\000\000\000\000\000\000\000\000\000\000\000\000\000\000".length() >>> "\000\000".length()] = 0x5D52 ^ 0x5D37; arrayOfByte[0x192F ^ 0x192E] = 0x3E70 ^ 0x3E38; arrayOfByte[0x5F65 ^ 0x5F63] = 0x68F3 ^ 0x689C; arrayOfByte["\000\000\000\000\000\000\000\000\000\000\000\000\000\000\000\000\000\000\000\000\000\000\000\000\000\000\000\000\000\000\000\000\000\000\000\000".length() >>> "\000\000".length()] = 0x162A ^ 0x1667; arrayOfByte[0x4954 ^ 0x495C] = 344 >>> "\000\000".length(); arrayOfByte["\000\000\000\000\000\000\000\000".length() >>> "\000\000".length()] = 0x6BBF ^ 0x6BD0; arrayOfByte["\000\000\000\000\000\000\000\000\000\000\000\000\000\000\000\000".length() >>> "\000\000".length()] = 0x39CF ^ 0x399C;
/*     */   }
/*     */ }


/* Location:              D:\Deobfuscator-master\test\deobf2\GOV.jar!\Class19.class
 * Java compiler version: 8 (52.0)
 * JD-Core Version:       1.1.3
 */